premvai/__init__.py
premvai/perceptron.py
premvai_premsaisahoo-0.0.6.dist-info/LICENSE
premvai_premsaisahoo-0.0.6.dist-info/METADATA
premvai_premsaisahoo-0.0.6.dist-info/WHEEL
premvai_premsaisahoo-0.0.6.dist-info/top_level.txt
premvai_premsaisahoo-0.0.6.dist-info/RECORD
